[
  {
    "degree": "Bachelor of Engineering in Electronics and Communication (B.E. ECE)",
    "where": "PPG Institute of Technology",
    "place": "Coimbatore affiliated to Anna University",
    "year": 2012,
    "mark": 71.70
  }, {
    "degree": "H.S.C",
    "where": "Vidya Vikasini Matric Hr. Sec. School",
    "place": "Coimbatore",
    "year": 2008,
    "mark": 81.83
  }, {
    "degree": "S.S.C",
    "where": "Stanes Anglo Indian Hr. Sec. School",
    "place": "Coonoor",
    "year": 2006,
    "mark": 76.4
  }
]